<manifest alg="2" build="2018.0.0.379" opt="false" iceEnabled="true" iceMarkupVersion="2" iceEnabledOptions="link,responsive,cachebuster,textStyling" exportTarget="other" domain="sugarcommunity.github.io" resolutions="1x" timestamp="1626917520570">
  <folder name="images">
    <file name="449974.jpg" crc="473676835" seo="true" ref="av-1">
      <caption webpage="av-1" alt=""/>
    </file>
    <file name="488499-800x538.jpg" crc="87524878" seo="true" ref="av-1">
      <caption webpage="av-1" alt=""/>
    </file>
    <file name="下載.jpg" crc="157400853" seo="true" ref="av-1">
      <caption webpage="av-1" alt=""/>
    </file>
    <file name="5.png" crc="361354441" seo="true" ref="membership-page">
      <caption webpage="membership-page" alt=""/>
    </file>
  </folder>
  <folder name="css">
    <file name="site_global.css" crc="444006867"/>
    <file name="page9-copy.css" crc="3957761549" ref="page9-copy"/>
    <file name="page16-copy.css" crc="185829921" ref="page16-copy"/>
    <file name="page2-copy.css" crc="201127891" ref="page2-copy"/>
    <file name="page10-copy.css" crc="3797250749" ref="page10-copy"/>
    <file name="page10.css" crc="475763368" ref="page10"/>
    <file name="page3-copy.css" crc="3795920559" ref="page3-copy"/>
    <file name="paeg17.css" crc="4206317302" ref="paeg17"/>
    <file name="page11.css" crc="3840483024" ref="page11"/>
    <file name="page4-copy.css" crc="360079842" ref="page4-copy"/>
    <file name="paeg14.css" crc="4952656" ref="paeg14"/>
    <file name="page5-copy.css" crc="51994193" ref="page5-copy"/>
    <file name="paeg18.css" crc="143938279" ref="paeg18"/>
    <file name="page12.css" crc="3898162815" ref="page12"/>
    <file name="page7-copy.css" crc="127385364" ref="page7-copy"/>
    <file name="page1.css" crc="4070439418" ref="page1"/>
    <file name="page6-copy.css" crc="458925072" ref="page6-copy"/>
    <file name="page6.css" crc="4264669351" ref="page6"/>
    <file name="page8-copy.css" crc="79400599" ref="page8-copy"/>
    <file name="page2.css" crc="352029902" ref="page2"/>
    <file name="page8.css" crc="3978478953" ref="page8"/>
    <file name="page11-copy.css" crc="72241458" ref="page11-copy"/>
    <file name="page4.css" crc="4283849231" ref="page4"/>
    <file name="page16.css" crc="43726340" ref="page16"/>
    <file name="page3.css" crc="3773755704" ref="page3"/>
    <file name="index.css" crc="464078514" ref="index"/>
    <file name="page12-copy.css" crc="247997247" ref="page12-copy"/>
    <file name="page13.css" crc="478789562" ref="page13"/>
    <file name="page15.css" crc="3970781262" ref="page15"/>
    <file name="page13-copy.css" crc="223519826" ref="page13-copy"/>
    <file name="page5.css" crc="4194413521" ref="page5"/>
    <file name="page7.css" crc="4267564711" ref="page7"/>
    <file name="smart-phone-version.css" crc="3877709381" ref="smart-phone-version"/>
    <file name="paeg14-copy.css" crc="3980615822" ref="paeg14-copy"/>
    <file name="page9.css" crc="383975318" ref="page9"/>
    <file name="page1-copy.css" crc="4021346265" ref="page1-copy"/>
    <file name="page15-copy.css" crc="3787054935" ref="page15-copy"/>
    <file name="table-of-contents.css" crc="231535744" ref="table-of-contents"/>
    <file name="av-1.css" crc="4284701407" ref="av-1"/>
    <file name="av-2.css" crc="4081617619" ref="av-2"/>
    <file name="av-3.css" crc="3801260985" ref="av-3"/>
    <file name="av-4.css" crc="140832357" ref="av-4"/>
    <file name="av-5.css" crc="3929183299" ref="av-5"/>
    <file name="av-6.css" crc="4109188766" ref="av-6"/>
    <file name="av-7.css" crc="354785072" ref="av-7"/>
    <file name="membership-page.css" crc="267490019" ref="membership-page"/>
    <file name="adult.css" crc="75723069" ref="adult"/>
    <file name="smart-phone-version-copy.css" crc="142018021" ref="smart-phone-version-copy"/>
    <file name="av2-c.css" crc="3887481108" ref="av2-c"/>
    <file name="av6-c.css" crc="4112867899" ref="av6-c"/>
    <file name="av3-c.css" crc="3814042058" ref="av3-c"/>
    <file name="av4-c.css" crc="152629154" ref="av4-c"/>
    <file name="av5-c.css" crc="3793768371" ref="av5-c"/>
    <file name="av-1-c.css" crc="271629629" ref="av-1-c"/>
    <file name="av7-c.css" crc="86450872" ref="av7-c"/>
    <file name="secret-page.css" crc="274707465" ref="secret-page"/>
    <file name="secret-page-smve.css" crc="42353375" ref="secret-page-smve"/>
  </folder>
  <folder name="scripts">
    <file name="jquery-1.8.3.min.js" crc="209076791" ref="index:page1:page2:page4:page3:page13:page5:page9:page10:page11:paeg14:page12:page6:page8:page16:page7:page15:smart-phone-version:page1-copy:page9-copy:page2-copy:page3-copy:page4-copy:page5-copy:page6-copy:page7-copy:page8-copy:page11-copy:page12-copy:page13-copy:paeg14-copy:page15-copy:page16-copy:page10-copy:paeg17:paeg18:table-of-contents:av-1:av-2:av-3:av-4:av-5:av-6:av-7:membership-page:adult:smart-phone-version-copy:av-1-c:av2-c:av3-c:av4-c:av5-c:av6-c:av7-c:secret-page:secret-page-smve"/>
    <file name="museutils.js" crc="3803043152" ref="index:page1:page2:page4:page3:page13:page5:page9:page10:page11:paeg14:page12:page6:page8:page16:page7:page15:smart-phone-version:page1-copy:page9-copy:page2-copy:page3-copy:page4-copy:page5-copy:page6-copy:page7-copy:page8-copy:page11-copy:page12-copy:page13-copy:paeg14-copy:page15-copy:page16-copy:page10-copy:paeg17:paeg18:table-of-contents:av-1:av-2:av-3:av-4:av-5:av-6:av-7:membership-page:adult:smart-phone-version-copy:av-1-c:av2-c:av3-c:av4-c:av5-c:av6-c:av7-c:secret-page:secret-page-smve"/>
    <file name="whatinput.js" crc="86476730" ref="index:page1:page2:page4:page3:page13:page5:page9:page10:page11:paeg14:page12:page6:page8:page16:page7:page15:smart-phone-version:page1-copy:page9-copy:page2-copy:page3-copy:page4-copy:page5-copy:page6-copy:page7-copy:page8-copy:page11-copy:page12-copy:page13-copy:paeg14-copy:page15-copy:page16-copy:page10-copy:paeg17:paeg18:table-of-contents:av-1:av-2:av-3:av-4:av-5:av-6:av-7:membership-page:adult:smart-phone-version-copy:av-1-c:av2-c:av3-c:av4-c:av5-c:av6-c:av7-c:secret-page:secret-page-smve"/>
    <file name="museconfig.js" crc="380897831" ref="index:page1:page2:page4:page3:page13:page5:page9:page10:page11:paeg14:page12:page6:page8:page16:page7:page15:smart-phone-version:page1-copy:page9-copy:page2-copy:page3-copy:page4-copy:page5-copy:page6-copy:page7-copy:page8-copy:page11-copy:page12-copy:page13-copy:paeg14-copy:page15-copy:page16-copy:page10-copy:paeg17:paeg18:table-of-contents:av-1:av-2:av-3:av-4:av-5:av-6:av-7:membership-page:adult:smart-phone-version-copy:av-1-c:av2-c:av3-c:av4-c:av5-c:av6-c:av7-c:secret-page:secret-page-smve"/>
    <file name="jquery.watch.js" crc="99325471" ref="index:page1:page2:page4:page3:page13:page5:page9:page10:page11:paeg14:page12:page6:page8:page16:page7:page15:smart-phone-version:page1-copy:page9-copy:page2-copy:page3-copy:page4-copy:page5-copy:page6-copy:page7-copy:page8-copy:page11-copy:page12-copy:page13-copy:paeg14-copy:page15-copy:page16-copy:page10-copy:paeg17:paeg18:table-of-contents:av-1:av-2:av-3:av-4:av-5:av-6:av-7:membership-page:adult:smart-phone-version-copy:av-1-c:av2-c:av3-c:av4-c:av5-c:av6-c:av7-c:secret-page:secret-page-smve"/>
    <file name="require.js" crc="4157109226" ref="index:page1:page2:page4:page3:page13:page5:page9:page10:page11:paeg14:page12:page6:page8:page16:page7:page15:smart-phone-version:page1-copy:page9-copy:page2-copy:page3-copy:page4-copy:page5-copy:page6-copy:page7-copy:page8-copy:page11-copy:page12-copy:page13-copy:paeg14-copy:page15-copy:page16-copy:page10-copy:paeg17:paeg18:table-of-contents:av-1:av-2:av-3:av-4:av-5:av-6:av-7:membership-page:adult:smart-phone-version-copy:av-1-c:av2-c:av3-c:av4-c:av5-c:av6-c:av7-c:secret-page:secret-page-smve"/>
  </folder>
  <file name="index.html" crc="69788881" seo="true" mt="1619117506298" redirect="true"/>
  <file name="page1.html" crc="286382637" seo="true" mt="1619120410943" redirect="true"/>
  <file name="page2.html" crc="88882032" seo="true" mt="1619119864508" redirect="true"/>
  <file name="page4.html" crc="292137619" seo="true" mt="1619695997019" redirect="true"/>
  <file name="page3.html" crc="4216945074" seo="true" mt="1620670713707" redirect="true"/>
  <file name="page13.html" crc="4104523317" seo="true" mt="1619694371672" redirect="true"/>
  <file name="page5.html" crc="317047871" seo="true" mt="1619695274053" redirect="true"/>
  <file name="page9.html" crc="3993776310" seo="true" mt="1619120979157" redirect="true"/>
  <file name="page10.html" crc="3923713738" seo="true" mt="1619121117160" redirect="true"/>
  <file name="page11.html" crc="4106814961" seo="true" mt="1619694961883" redirect="true"/>
  <file name="paeg14.html" crc="509465006" seo="true" mt="1619694426758" redirect="true"/>
  <file name="page12.html" crc="241277522" seo="true" mt="1619694291512" redirect="true"/>
  <file name="page6.html" crc="4010180843" seo="true" mt="1619695217388" redirect="true"/>
  <file name="page8.html" crc="382059882" seo="true" mt="1619695146971" redirect="true"/>
  <file name="page16.html" crc="403400401" seo="true" mt="1619694681790" redirect="true"/>
  <file name="page7.html" crc="196030257" seo="true" mt="1619120653166" redirect="true"/>
  <file name="page15.html" crc="470516921" seo="true" mt="1619045818241" redirect="true"/>
  <file name="smart-phone-version.html" crc="3900487327" seo="true" mt="1619117839893" redirect="true"/>
  <file name="page1-copy.html" crc="4048166194" seo="true" mt="1619120606183" redirect="true"/>
  <file name="page9-copy.html" crc="267933863" seo="true" mt="1619121030851" redirect="true"/>
  <file name="page2-copy.html" crc="3934270161" seo="true" mt="1619048859673" redirect="true"/>
  <file name="page3-copy.html" crc="488876399" seo="true" mt="1620670786847" redirect="true"/>
  <file name="page4-copy.html" crc="405530130" seo="true" mt="1619695895605" redirect="true"/>
  <file name="page5-copy.html" crc="4065281472" seo="true" mt="1619695314775" redirect="true"/>
  <file name="page6-copy.html" crc="528569808" seo="true" mt="1619695238827" redirect="true"/>
  <file name="page7-copy.html" crc="285507522" seo="true" mt="1619120663272" redirect="true"/>
  <file name="page8-copy.html" crc="4004700481" seo="true" mt="1619695135278" redirect="true"/>
  <file name="page11-copy.html" crc="3926460824" seo="true" mt="1619694941183" redirect="true"/>
  <file name="page12-copy.html" crc="4159303425" seo="true" mt="1619694194220" redirect="true"/>
  <file name="page13-copy.html" crc="4132997011" seo="true" mt="1619694361676" redirect="true"/>
  <file name="paeg14-copy.html" crc="3886383401" seo="true" mt="1619694413144" redirect="true"/>
  <file name="page15-copy.html" crc="363156202" seo="true" mt="1619049352284" redirect="true"/>
  <file name="page16-copy.html" crc="4099081228" seo="true" mt="1619694692800" redirect="true"/>
  <file name="page10-copy.html" crc="3769639601" seo="true" mt="1619050445646" redirect="true"/>
  <file name="paeg17.html" crc="4140233918" seo="true" mt="1619117436520" redirect="true"/>
  <file name="paeg18.html" crc="3887056211" seo="true" mt="1622834672728" redirect="true"/>
  <file name="table-of-contents.html" crc="3889135010" seo="true" mt="1623841134136" redirect="true"/>
  <file name="av-1.html" crc="285875811" seo="true" mt="1622952532290" redirect="true"/>
  <file name="av-2.html" crc="3793282468" seo="true" mt="1623115946871" redirect="true"/>
  <file name="av-3.html" crc="300971644" seo="true" mt="1623317724098" redirect="true"/>
  <file name="av-4.html" crc="232214321" seo="true" mt="1623568364076" redirect="true"/>
  <file name="av-5.html" crc="4048136074" seo="true" mt="1623656890353" redirect="true"/>
  <file name="av-6.html" crc="437391893" seo="true" mt="1623743420021" redirect="true"/>
  <file name="av-7.html" crc="4061410516" seo="true" mt="1623841008898" redirect="true"/>
  <file name="membership-page.html" crc="325284065" seo="true" mt="1624933425095" redirect="true"/>
  <file name="adult.html" crc="3946675870" seo="true" mt="1626917173787" redirect="true"/>
  <file name="smart-phone-version-copy.html" crc="3950354084" seo="true" mt="1626917173784" redirect="true"/>
  <file name="av-1-c.html" crc="4281993687" seo="true" mt="1626913982121" redirect="true"/>
  <file name="av2-c.html" crc="4178986391" seo="true" mt="1626914039761" redirect="true"/>
  <file name="av3-c.html" crc="494315266" seo="true" mt="1626914053917" redirect="true"/>
  <file name="av4-c.html" crc="290566583" seo="true" mt="1626914072227" redirect="true"/>
  <file name="av5-c.html" crc="207808113" seo="true" mt="1626914101221" redirect="true"/>
  <file name="av6-c.html" crc="4173472345" seo="true" mt="1626914118028" redirect="true"/>
  <file name="av7-c.html" crc="3828033015" seo="true" mt="1626914136726" redirect="true"/>
  <file name="secret-page.html" crc="447586444" seo="true" mt="1626917173792" redirect="true"/>
  <file name="secret-page-smve.html" crc="151037559" seo="true" mt="1626917514822" redirect="true"/>
</manifest>